{"slug":"Lowestoft/LowestoftMoncktonAvefromSept2007","name":"Lowestoft / Lowestoft Monckton Ave from Sept 2007","location":{"lat":52.483,"long":1.727,"altitude":18},"weatherData":[{"year":1914,"month":1,"tmax":5.2,"tmin":0.7,"af":52,"rain":null,"sun":null},{"year":1914,"month":2,"tmax":9.2,"tmin":3.5,"af":28,"rain":null,"sun":null},{"year":1914,"month":3,"tmax":null,"tmin":null,"af":null,"rain":null,"sun":null},{"year":1914,"month":4,"tmax":12.9,"tmin":5.3,"af":18,"rain":null,"sun":null},{"year":1914,"month":5,"tmax":13.7,"tmin":7.2,"af":38,"rain":null,"sun":null},{"year":1914,"month":6,"tmax":16.2,"tmin":10.4,"af":38,"rain":null,"sun":null},{"year":1914,"month":7,"tmax":19.8,"tmin":13,"af":53,"rain":null,"sun":null},{"year":1914,"month":8,"tmax":20.3,"tmin":13.7,"af":17,"rain":null,"sun":null},{"year":1914,"month":9,"tmax":17.7,"tmin":11.4,"af":29,"rain":null,"sun":null},{"year":1914,"month":10,"tmax":14.1,"tmin":9.1,"af":45,"rain":null,"sun":null},{"year":1914,"month":11,"tmax":9.9,"tmin":5,"af":80,"rain":null,"sun":null},{"year":1914,"month":12,"tmax":8.2,"tmin":3.3,"af":141,"rain":null,"sun":null},{"year":1915,"month":1,"tmax":6.3,"tmin":2.3,"af":75,"rain":null,"sun":null},{"year":1915,"month":2,"tmax":7.3,"tmin":2.3,"af":64,"rain":null,"sun":null},{"year":1915,"month":3,"tmax":8.3,"tmin":2.3,"af":43,"rain":null,"sun":null},{"year":1915,"month":4,"tmax":10.4,"tmin":4.1,"af":25,"rain":null,"sun":null},{"year":1915,"month":5,"tmax":12.4,"tmin":6.9,"af":50,"rain":null,"sun":null},{"year":1915,"month":6,"tmax":16.2,"tmin":10.3,"af":39,"rain":null,"sun":null},{"year":1915,"month":7,"tmax":19,"tmin":12,"af":123,"rain":null,"sun":null},{"year":1915,"month":8,"tmax":18.9,"tmin":12.3,"af":29,"rain":null,"sun":null},{"year":1915,"month":9,"tmax":17.7,"tmin":11.7,"af":62,"rain":null,"sun":null},{"year":1915,"month":10,"tmax":12.9,"tmin":8.4,"af":67,"rain":null,"sun":null},{"year":1915,"month":11,"tmax":7.9,"tmin":2.6,"af":69,"rain":null,"sun":null},{"year":1915,"month":12,"tmax":8.2,"tmin":3.5,"af":91,"rain":null,"sun":null},{"year":1916,"month":1,"tmax":9.4,"tmin":4.3,"af":36,"rain":null,"sun":null},{"year":1916,"month":2,"tmax":6.9,"tmin":1.3,"af":92,"rain":null,"sun":null},{"year":1916,"month":3,"tmax":6.5,"tmin":1.7,"af":69,"rain":null,"sun":null},{"year":1916,"month":4,"tmax":11,"tmin":4.6,"af":45,"rain":null,"sun":null},{"year":1916,"month":5,"tmax":14.4,"tmin":8.5,"af":38,"rain":null,"sun":null},{"year":1916,"month":6,"tmax":14.8,"tmin":8.6,"af":88,"rain":null,"sun":null},{"year":1916,"month":7,"tmax":17.3,"tmin":11.5,"af":20,"rain":null,"sun":null},{"year":1916,"month":8,"tmax":19,"tmin":12.7,"af":75,"rain":null,"sun":null},{"year":1916,"month":9,"tmax":16.2,"tmin":10.6,"af":31,"rain":null,"sun":null},{"year":1916,"month":10,"tmax":null,"tmin":null,"af":null,"rain":null,"sun":null},{"year":1916,"month":11,"tmax":null,"tmin":null,"af":null,"rain":null,"sun":null},{"year":1916,"month":12,"tmax":6.3,"tmin":1.3,"af":75,"rain":null,"sun":null},{"year":1917,"month":1,"tmax":4.2,"tmin":0.6,"af":52,"rain":null,"sun":null},{"year":1917,"month":2,"tmax":3.8,"tmin":-0.8,"af":19,"rain":null,"sun":null},{"year":1917,"month":3,"tmax":5.7,"tmin":-0.2,"af":51,"rain":null,"sun":null},{"year":1917,"month":4,"tmax":7.8,"tmin":1.4,"af":67,"rain":null,"sun":null},{"year":1917,"month":5,"tmax":null,"tmin":null,"af":null,"rain":null,"sun":null},{"year":1917,"month":6,"tmax":null,"tmin":null,"af":null,"rain":null,"sun":null},{"year":1917,"month":7,"tmax":null,"tmin":null,"af":null,"rain":null,"sun":null},{"year":1917,"month":8,"tmax":null,"tmin":null,"af":null,"rain":null,"sun":null},{"year":1917,"month":9,"tmax":null,"tmin":null,"af":null,"rain":null,"sun":null},{"year":1917,"month":10,"tmax":null,"tmin":null,"af":null,"rain":null,"sun":null},{"year":1917,"month":11,"tmax":null,"tmin":null,"af":null,"rain":null,"sun":null},{"year":1917,"month":12,"tmax":null,"tmin":null,"af":null,"rain":null,"sun":null},{"year":1919,"month":1,"tmax":null,"tmin":null,"af":null,"rain":null,"sun":null},{"year":1919,"month":2,"tmax":null,"tmin":null,"af":null,"rain":null,"sun":null},{"year":1919,"month":3,"tmax":null,"tmin":null,"af":null,"rain":null,"sun":null},{"year":1919,"month":4,"tmax":null,"tmin":null,"af":null,"rain":null,"sun":null},{"year":1919,"month":5,"tmax":null,"tmin":null,"af":null,"rain":null,"sun":null},{"year":1919,"month":6,"tmax":null,"tmin":null,"af":null,"rain":null,"sun":null},{"year":1919,"month":7,"tmax":null,"tmin":null,"af":null,"rain":null,"sun":null},{"year":1919,"month":8,"tmax":null,"tmin":null,"af":null,"rain":null,"sun":null},{"year":1919,"month":9,"tmax":null,"tmin":null,"af":null,"rain":null,"sun":null},{"year":1919,"month":10,"tmax":null,"tmin":null,"af":null,"rain":null,"sun":null},{"year":1919,"month":11,"tmax":null,"tmin":null,"af":null,"rain":null,"sun":null},{"year":1919,"month":12,"tmax":7.4,"tmin":2.3,"af":80,"rain":null,"sun":null},{"year":1920,"month":1,"tmax":7.8,"tmin":2.3,"af":52,"rain":null,"sun":null},{"year":1920,"month":2,"tmax":8.9,"tmin":3.7,"af":9,"rain":null,"sun":null},{"year":1920,"month":3,"tmax":10.6,"tmin":3.9,"af":22,"rain":null,"sun":null},{"year":1920,"month":4,"tmax":null,"tmin":null,"af":null,"rain":null,"sun":null},{"year":1920,"month":5,"tmax":null,"tmin":null,"af":null,"rain":null,"sun":null},{"year":1920,"month":6,"tmax":null,"tmin":null,"af":null,"rain":null,"sun":null},{"year":1920,"month":7,"tmax":null,"tmin":null,"af":null,"rain":null,"sun":null},{"year":1920,"month":8,"tmax":null,"tmin":null,"af":null,"rain":null,"sun":null},{"year":1920,"month":9,"tmax":null,"tmin":null,"af":null,"rain":null,"sun":null},{"year":1920,"month":10,"tmax":null,"tmin":null,"af":null,"rain":null,"sun":null},{"year":1920,"month":11,"tmax":null,"tmin":null,"af":null,"rain":null,"sun":null},{"year":1920,"month":12,"tmax":null,"tmin":null,"af":null,"rain":null,"sun":null},{"year":1921,"month":1,"tmax":null,"tmin":null,"af":null,"rain":null,"sun":null},{"year":1921,"month":2,"tmax":null,"tmin":null,"af":null,"rain":null,"sun":null},{"year":1921,"month":3,"tmax":11.3,"tmin":4,"af":20,"rain":163,"sun":null},{"year":1921,"month":4,"tmax":225,"tmin":null,"af":null,"rain":null,"sun":null},{"year":1921,"month":5,"tmax":14.2,"tmin":8.1,"af":25,"rain":269,"sun":null},{"year":1921,"month":6,"tmax":16.2,"tmin":10.6,"af":15,"rain":194,"sun":null},{"year":1921,"month":7,"tmax":20.7,"tmin":13.6,"af":11,"rain":275,"sun":null},{"year":1921,"month":8,"tmax":20.6,"tmin":13.4,"af":47,"rain":207,"sun":null},{"year":1921,"month":9,"tmax":19.1,"tmin":11.7,"af":36,"rain":176,"sun":null},{"year":1921,"month":10,"tmax":17.1,"tmin":10.2,"af":25,"rain":145,"sun":null},{"year":1921,"month":11,"tmax":8.2,"tmin":3.2,"af":70,"rain":84,"sun":null},{"year":1921,"month":12,"tmax":8.9,"tmin":3.8,"af":48,"rain":43,"sun":null},{"year":1922,"month":1,"tmax":5,"tmin":1.3,"af":113,"rain":34,"sun":null},{"year":1922,"month":2,"tmax":6.9,"tmin":1.9,"af":53,"rain":104,"sun":null},{"year":1922,"month":3,"tmax":7.2,"tmin":2.6,"af":44,"rain":108,"sun":null},{"year":1922,"month":4,"tmax":8.9,"tmin":2.9,"af":58,"rain":195,"sun":null},{"year":1922,"month":5,"tmax":16.3,"tmin":8.2,"af":20,"rain":289,"sun":null},{"year":1922,"month":6,"tmax":17,"tmin":10.4,"af":39,"rain":242,"sun":null},{"year":1922,"month":7,"tmax":17.4,"tmin":11.3,"af":89,"rain":162,"sun":null},{"year":1922,"month":8,"tmax":18,"tmin":10.9,"af":27,"rain":181,"sun":null},{"year":1922,"month":9,"tmax":16,"tmin":10.2,"af":63,"rain":178,"sun":null}]}