{"slug":"Oxford","name":"Oxford","location":{"latLong":" Lat 51.761 Lon -1.262","altitude":63},"weatherData":[{"year":1853,"month":1,"tmax":8.4,"tmin":2.7,"af":4,"rain":62.8,"sun":null},{"year":1853,"month":2,"tmax":3.2,"tmin":-1.8,"af":19,"rain":29.3,"sun":null},{"year":1853,"month":3,"tmax":7.7,"tmin":-0.6,"af":20,"rain":25.9,"sun":null},{"year":1853,"month":4,"tmax":12.6,"tmin":4.5,"af":0,"rain":60.1,"sun":null},{"year":1853,"month":5,"tmax":16.8,"tmin":6.1,"af":0,"rain":59.5,"sun":null},{"year":1853,"month":6,"tmax":20.1,"tmin":10.7,"af":0,"rain":82,"sun":null},{"year":1853,"month":7,"tmax":21.2,"tmin":12.2,"af":0,"rain":86.2,"sun":null},{"year":1853,"month":8,"tmax":20.2,"tmin":10.8,"af":0,"rain":72.3,"sun":null},{"year":1853,"month":9,"tmax":17.3,"tmin":8.4,"af":0,"rain":51.3,"sun":null},{"year":1853,"month":10,"tmax":13.9,"tmin":7.4,"af":0,"rain":102.3,"sun":null},{"year":1853,"month":11,"tmax":8.7,"tmin":2.3,"af":10,"rain":49.6,"sun":null},{"year":1853,"month":12,"tmax":3.7,"tmin":-1.3,"af":19,"rain":10.7,"sun":null},{"year":1854,"month":1,"tmax":6.7,"tmin":1.5,"af":11,"rain":54.5,"sun":null}]}